nexus_utils/__init__.py
nexus_utils/config_utils.py
nexus_utils/database_utils.py
nexus_utils/datetime_utils.py
nexus_utils/email_handler.py
nexus_utils/flatfile_utils.py
nexus_utils/package_utils.py
nexus_utils/password_utils.py
nexus_utils/string_utils.py
nexus_utilities-0.8.0.dist-info/LICENSE.txt
nexus_utilities-0.8.0.dist-info/METADATA
nexus_utilities-0.8.0.dist-info/WHEEL
nexus_utilities-0.8.0.dist-info/top_level.txt
nexus_utilities-0.8.0.dist-info/RECORD
